ftp_core_bindings_pyo3-0.1.796.dist-info/METADATA
ftp_core_bindings_pyo3-0.1.796.dist-info/WHEEL
ftp_core_bindings_pyo3/__init__.py
ftp_core_bindings_pyo3/ftp_core_bindings_pyo3.cpython-312-x86_64-linux-gnu.so
ftp_core_bindings_pyo3-0.1.796.dist-info/RECORD
