Metadata-Version: 2.4
Name: ftp_core_bindings_pyo3
Version: 0.1.796
Summary: Python bindings for FTP Core library
Keywords: ftp,calculator,python
Author: Votre Nom <votre.email@example.com>
Author-email: Votre Nom <votre.email@example.com>
License: MIT OR Apache-2.0
Project-URL: Source Code, https://github.com/votre-username/votre-repo
